nar/__init__.py
nar/gardener.py
nar/utils.py
nar.py-0.0.8.dist-info/METADATA
nar.py-0.0.8.dist-info/WHEEL
nar.py-0.0.8.dist-info/top_level.txt
nar.py-0.0.8.dist-info/RECORD
